agcli/__init__.py
agcli/agcli.py
agcli/assets/+.bmp
agcli/docparser/__init__.py
agcli/docparser/docopt_parser.py
agcli/docparser/docparser.py
agcli/docparser/explainshell_parser.py
agcli/docparser/naive_parser.py
agcli/docparser/new_docopt.py
agcli/docparser/parameters_extractor.py
agcli/event/__init__.py
agcli/event/event_handler.py
agcli/gui/__init__.py
agcli/gui/command_notebook.py
agcli/gui/command_panel.py
agcli/gui/drag_and_drop.py
agcli/gui/information_panel.py
agcli/gui/main_window.py
agcli/gui/component/__init__.py
agcli/gui/component/argument_component.py
agcli/gui/component/base_argument_component.py
agcli/gui/component/base_component.py
agcli/gui/component/custom_collapsible_pane.py
agcli/gui/component/custom_notebook.py
agcli/gui/component/custom_widget.py
agcli/gui/component/option_component.py
agcli/gui/component/option_name.py
agcli/gui/component/parameter_component.py
agcli/gui/component/subcommand_component.py
agcli/interface/__init__.py
agcli/interface/interface_generator.py
agcli/output/interfaces/interface_wc.yaml
agcli/output/templates/template_default_wc.yaml
agcli/template/__init__.py
agcli/template/cli_parser.py
agcli/template/template_generator.py
agcli/utils/__init__.py
agcli/utils/file_handler.py
agcli/utils/terminal.py
agcli/utils/yaml.py
agcli-1.5.1.dist-info/DESCRIPTION.rst
agcli-1.5.1.dist-info/METADATA
agcli-1.5.1.dist-info/RECORD
agcli-1.5.1.dist-info/WHEEL
agcli-1.5.1.dist-info/entry_points.txt
agcli-1.5.1.dist-info/metadata.json
agcli-1.5.1.dist-info/top_level.txt
