Metadata-Version: 2.0
Name: agcli
Version: 1.5.1
Summary: A GUI that helps building instructions for the CLI
Home-page: https://gitlab.com/MaximeDeWolf/agcli
Author: Maxime De Wolf
License: LGPL3
Keywords: gui cli shell terminal instruction
Platform: UNKNOWN
Classifier: Development Status :: 5 - Production/Stable
Classifier: Intended Audience :: Developers
Classifier: Intended Audience :: Education
Classifier: Intended Audience :: End Users/Desktop
Classifier: Topic :: Education :: Computer Aided Instruction (CAI)
Classifier: Topic :: Scientific/Engineering :: Human Machine Interfaces
Classifier: Topic :: System :: Shells
Classifier: License :: OSI Approved :: GNU Lesser General Public License v3 (LGPLv3)
Classifier: Programming Language :: Python :: 3.6
Requires-Python: >=3.6
Requires-Dist: ruamel.yaml (>=0.15)
Requires-Dist: urllib3 (>=1.23)
Requires-Dist: certifi (>=2019.6)
Requires-Dist: wxPython (>=4.0)
Requires-Dist: setuptools
